{
  "index.html-crop-distribution": {
    "precise-div-noid-overlay-switch-btn-4-3-8-ä½œç‰©é€‰æ‹©": {
      "name": "div: ðŸŒ¾            ä½œç‰©é€‰æ‹©",
      "content": "- **å åŠ åŠŸèƒ½æŒ‰é’®**: 2ä¸ªå¤šé€‰æŒ‰é’®ï¼Œå¼€å¯é™„åŠ åŠŸèƒ½\n  - ðŸ“± è®¾å¤‡ç›‘æŽ§ (è¦†ç›–è®¾å¤‡ä½ç½®ä¿¡æ¯)\n  - ðŸŒ¾ ä½œç‰©é€‰æ‹© (ä½œç‰©å›¾å±‚ç­›é€‰å™¨)",
      "timestamp": "2025/8/14 15:13:43",
      "elementId": "precise-div-noid-overlay-switch-btn-4-3-8-ä½œç‰©é€‰æ‹©",
      "targetInfo": {
        "smartSelector": "html > body > div.function-switch-bar > div.overlay-switch-btn[data-function=\"crop-selection\"]:nth-of-type(2)",
        "elementFingerprint": {
          "tagName": "DIV",
          "className": "overlay-switch-btn",
          "textContent": "ðŸŒ¾\n            ä½œç‰©é€‰æ‹©",
          "attributes": {
            "data-function": "crop-selection"
          },
          "position": {
            "offsetLeft": 642,
            "offsetTop": 12,
            "offsetWidth": 100,
            "offsetHeight": 40
          },
          "chartType": null
        },
        "fallbackSelector": "div.overlay-switch-btn",
        "textContent": "ðŸŒ¾\n            ä½œç‰©é€‰æ‹©",
        "pageUrl": "http://localhost:3000/prototype/index.html",
        "timestamp": "2025-08-14T07:13:43.573Z"
      },
      "lastModified": "2025-08-14T07:13:43.604Z"
    },
    "precise-div-noid-main-switch-btn-5-0-0": {
      "name": "div: ðŸŒ¾            ...",
      "content": "- **ä¸»åŠŸèƒ½æŒ‰é’®**: 5ä¸ªå•é€‰æŒ‰é’®ï¼Œåˆ‡æ¢ä¸åŒé¡µé¢åŠŸèƒ½\n  - ðŸŒ¾ ä½œç‰©åˆ†å¸ƒ (å½“å‰é¡µé¢)\n  - ðŸ“Š é•¿åŠ¿åˆ†æž (growth-analysis.html)\n  - ðŸ“ˆ äº§é‡é¢„ä¼° (yield-estimation.html)\n  - ðŸŒ¤ï¸ æ°”è±¡ç›‘æµ‹ (weather-monitoring.html)\n  - âš ï¸ ç¾å®³å®šæŸ (disaster-monitoring.html)",
      "timestamp": "2025/8/14 15:14:02",
      "elementId": "precise-div-noid-main-switch-btn-5-0-0",
      "targetInfo": {
        "smartSelector": "html > body > div.function-switch-bar > div.main-switch-buttons > div.main-switch-btn.active[data-function=\"crop-distribution\"]",
        "elementFingerprint": {
          "tagName": "DIV",
          "className": "main-switch-btn active",
          "textContent": "ðŸŒ¾\n                ä½œç‰©åˆ†å¸ƒ",
          "attributes": {
            "data-function": "crop-distribution"
          },
          "position": {
            "offsetLeft": 20,
            "offsetTop": 12,
            "offsetWidth": 80,
            "offsetHeight": 40
          },
          "chartType": null
        },
        "fallbackSelector": "div.main-switch-btn.active",
        "textContent": "ðŸŒ¾\n                ä½œç‰©åˆ†å¸ƒ",
        "pageUrl": "http://localhost:3000/prototype/index.html",
        "timestamp": "2025-08-14T07:14:02.033Z"
      },
      "lastModified": "2025-08-14T07:14:02.127Z"
    }
  }
}
